pkg/__init__.py
vuln_instrumentation-0.0.3.dist-info/METADATA
vuln_instrumentation-0.0.3.dist-info/WHEEL
vuln_instrumentation-0.0.3.dist-info/top_level.txt
vuln_instrumentation-0.0.3.dist-info/RECORD
