Metadata-Version: 2.1
Name: vuln-instrumentation
Version: 0.0.3
Summary: Instrumentation Library
Home-page: https://github.com/VulnCorp/vuln-utils
Author: VulnCorp
Author-email: admin@vulncorp.com
License: UNKNOWN
Project-URL: Bug Tracker, https://github.com/VulnCorp/vuln-instrumentation/issues
Platform: UNKNOWN
Classifier: Programming Language :: Python :: 3
Classifier: License :: OSI Approved :: MIT License
Classifier: Operating System :: OS Independent
Requires-Python: >=3.6
Requires-Dist: vuln-utils (==0.0.3)
